tutor_contrib_panorama-19.1.0.dist-info/licenses/LICENSE
tutorpanorama/__about__.py
tutorpanorama/__init__.py
tutorpanorama/plugin.py
tutorpanorama/patches/.gitignore
tutorpanorama/patches/k8s-deployments
tutorpanorama/patches/k8s-jobs
tutorpanorama/patches/kustomization
tutorpanorama/patches/kustomization-configmapgenerator
tutorpanorama/patches/local-docker-compose-jobs-services
tutorpanorama/patches/local-docker-compose-services
tutorpanorama/patches/mfe-lms-development-settings
tutorpanorama/patches/mfe-lms-production-settings
tutorpanorama/patches/openedx-dockerfile-post-python-requirements
tutorpanorama/patches/openedx-lms-common-settings
tutorpanorama/templates/panorama/apps/.gitignore
tutorpanorama/templates/panorama/apps/panorama-elt/crontab
tutorpanorama/templates/panorama/apps/panorama-elt/fluent-bit-local.conf
tutorpanorama/templates/panorama/apps/panorama-elt/fluent-bit.conf
tutorpanorama/templates/panorama/apps/panorama-elt/panorama_openedx_settings.yaml
tutorpanorama/templates/panorama/apps/panorama-elt/parsers.conf
tutorpanorama/templates/panorama/build/.gitignore
tutorpanorama/templates/panorama/build/panorama-elt/Dockerfile
tutorpanorama/templates/panorama/build/panorama-elt-logs/Dockerfile
tutorpanorama/templates/panorama/tasks/.gitignore
tutorpanorama/templates/panorama/tasks/lms/init
tutorpanorama/templates/panorama/tasks/panorama-elt/init
tutor_contrib_panorama-19.1.0.dist-info/METADATA
tutor_contrib_panorama-19.1.0.dist-info/WHEEL
tutor_contrib_panorama-19.1.0.dist-info/entry_points.txt
tutor_contrib_panorama-19.1.0.dist-info/top_level.txt
tutor_contrib_panorama-19.1.0.dist-info/RECORD
