Metadata-Version: 2.4
Name: tutor-contrib-panorama
Version: 19.1.0
Summary: Tutor plugin for Panorama Analytics
Home-page: https://github.com/aulasneo/tutor-contrib-panorama
Author: Aulsneo
Author-email: andres@aulasneo.com
Maintainer: Aulasneo
License: AGPLv3
Project-URL: Code, https://github.com/aulasneo/tutor-contrib-panorama
Project-URL: Issue tracker, https://github.com/aulasneo/tutor-contrib-panorama/issues
Classifier: Development Status :: 5 - Production/Stable
Classifier: Intended Audience :: System Administrators
Classifier: License :: OSI Approved :: GNU Affero General Public License v3
Classifier: Operating System :: OS Independent
Classifier: Programming Language :: Python
Classifier: Programming Language :: Python :: 3.7
Classifier: Programming Language :: Python :: 3.8
Classifier: Programming Language :: Python :: 3.9
Classifier: Programming Language :: Python :: 3.10
Requires-Python: >=3.7
License-File: LICENSE
Requires-Dist: tutor<20.0.0,>=19.0.0
Dynamic: author
Dynamic: author-email
Dynamic: classifier
Dynamic: description
Dynamic: description-content-type
Dynamic: home-page
Dynamic: license
Dynamic: license-file
Dynamic: maintainer
Dynamic: project-url
Dynamic: requires-dist
Dynamic: requires-python
Dynamic: summary
